LICENSE.md
setup.py
aiaa/sql/__init__.py
aiaa/utils/__init__.py
aiaa/utils/exception.py
aiaa/utils/logging.py
aiaa_framework.egg-info/PKG-INFO
aiaa_framework.egg-info/SOURCES.txt
aiaa_framework.egg-info/dependency_links.txt
aiaa_framework.egg-info/requires.txt
aiaa_framework.egg-info/top_level.txt